typecmd/__init__.py
typecmd/yaml2json.py
typecmd-1.0.1.dist-info/METADATA
typecmd-1.0.1.dist-info/WHEEL
typecmd-1.0.1.dist-info/entry_points.txt
typecmd-1.0.1.dist-info/RECORD
